quant/__init__.py
quant/core/Abstract.py
quant/core/DB.py
quant/core/QuantEngine.py
quant/core/Selecter.py
quant/core/Spider.py
quant/core/Stats.py
quant/core/Worker.py
quant/core/__init__.py
quant/selecter/DailyStrong.py
quant/selecter/DailyTrend.py
quant/selecter/Dma.py
quant/selecter/RealVolumeRate.py
quant/selecter/Wpkiller.py
quant/selecter/__init__.py
quant/spider/Baidu.py
quant/spider/Demo.py
quant/spider/Fund.py
quant/spider/Handicap.py
quant/spider/Index.py
quant/spider/LhbData.py
quant/spider/MinData.py
quant/spider/Stock.py
quant/spider/TouTiao.py
quant/spider/TouTiaoDetail.py
quant/spider/WeiXin.py
quant/spider/Yunpan.py
quant/spider/__init__.py
quant/stats/Average.py
quant/stats/ElSearch.py
quant/stats/MaCount.py
quant/stats/Pankou.py
quant/stats/RealTimeChange.py
quant/stats/Summary.py
quant/stats/TdxAnalyse.py
quant/stats/__init__.py
quant/strategy/__init__.py
quant/tools/SimpleCode.py
quant/tools/Util.py
quant/tools/__init__.py
test/__init__.py
test/elasticsearch.py
test/mango_test.py
sogaQuant-2.1.2.dist-info/LICENSE
sogaQuant-2.1.2.dist-info/METADATA
sogaQuant-2.1.2.dist-info/WHEEL
sogaQuant-2.1.2.dist-info/top_level.txt
sogaQuant-2.1.2.dist-info/RECORD
